hyper_client/__init__.py
hyper_client/base.py
hyper_client/config.py
hyper_client/controller.py
hyper_client/hyper.py
hyper_client/utils/__init__.py
hyper_client/utils/exceptions.py
hyper_client/utils/log.py
hyper_client/utils/misc.py
hyper_client-0.2.dist-info/METADATA
hyper_client-0.2.dist-info/WHEEL
hyper_client-0.2.dist-info/top_level.txt
hyper_client-0.2.dist-info/RECORD
