Metadata-Version: 2.1
Name: hyper-client
Version: 0.2
Summary: Snark Hyper Client
Home-page: https://github.com/activeloopai/hyper
Author: Activeloop
Author-email: support@activeloop.ai
License: UNKNOWN
Keywords: activeloop-hyper
Platform: UNKNOWN
Requires-Python: >=3
